EvoMSA/__init__.py
EvoMSA/back_prop.py
EvoMSA/base.py
EvoMSA/command_line.py
EvoMSA/competitions.py
EvoMSA/cython_utils.cp311-win_amd64.pyd
EvoMSA/cython_utils.pyx
EvoMSA/evodag.py
EvoMSA/model.py
EvoMSA/model_selection.py
EvoMSA/text_repr.py
EvoMSA/unique.py
EvoMSA/utils.py
EvoMSA/ConceptModelling/text_preprocessing.py
EvoMSA/ConceptModelling/thumbs_up_down.py
EvoMSA/ConceptModelling/data/ar.affective.words.json
EvoMSA/ConceptModelling/data/en.affective.words.json
EvoMSA/ConceptModelling/data/es.affective.words.json
EvoMSA/conf/aggressiveness.ar
EvoMSA/conf/aggressiveness.en
EvoMSA/conf/aggressiveness.es
EvoMSA/models/b4msa_Ar.tm
EvoMSA/models/b4msa_En.tm
EvoMSA/models/b4msa_Es.tm
EvoMSA/models/emo_Ar.tm
EvoMSA/models/emo_En.tm
EvoMSA/models/emo_Es.tm
EvoMSA/models/ha_Ar.tm
EvoMSA/models/ha_En.tm
EvoMSA/models/ha_Es.tm
EvoMSA/tests/__init__.py
EvoMSA/tests/test_back_prop.py
EvoMSA/tests/test_base.py
EvoMSA/tests/test_command_line.py
EvoMSA/tests/test_competitions.py
EvoMSA/tests/test_evodag.py
EvoMSA/tests/test_model.py
EvoMSA/tests/test_text_repr.py
EvoMSA/tests/test_thumbs_up_down.py
EvoMSA/tests/test_unique.py
EvoMSA/tests/test_utils.py
EvoMSA/tests/tweets.json
evomsa-2.0.14.dist-info/licenses/LICENSE
evomsa-2.0.14.dist-info/METADATA
evomsa-2.0.14.dist-info/WHEEL
evomsa-2.0.14.dist-info/top_level.txt
evomsa-2.0.14.dist-info/RECORD
