Metadata-Version: 2.4
Name: EvoMSA
Version: 2.0.14
Summary: Set of algorithms to detect the dialect of a given text
License-Expression: Apache-2.0
Project-URL: Homepage, https://evomsa.readthedocs.io
Project-URL: Repository, https://github.com/INGEOTEC/EvoMSA
Project-URL: Issues, https://github.com/INGEOTEC/EvoMSA/issues
Classifier: Development Status :: 5 - Production/Stable
Classifier: Environment :: Console
Classifier: Intended Audience :: Developers
Classifier: Intended Audience :: Information Technology
Classifier: Intended Audience :: Science/Research
Classifier: Operating System :: OS Independent
Classifier: Programming Language :: Python
Classifier: Topic :: Scientific/Engineering :: Artificial Intelligence
License-File: LICENSE
Requires-Dist: numpy
Requires-Dist: scikit-learn>=1.3.0
Requires-Dist: cython
Requires-Dist: microtc
Requires-Dist: b4msa
Requires-Dist: ingeoml>=0.0.25
Dynamic: license-file
